.travis.yml
LICENSE
MANIFEST.in
README.rst
setup.cfg
setup.py
tox.ini
Mopidy_Plex.egg-info/PKG-INFO
Mopidy_Plex.egg-info/SOURCES.txt
Mopidy_Plex.egg-info/dependency_links.txt
Mopidy_Plex.egg-info/entry_points.txt
Mopidy_Plex.egg-info/not-zip-safe
Mopidy_Plex.egg-info/requires.txt
Mopidy_Plex.egg-info/top_level.txt
mopidy_plex/__init__.py
mopidy_plex/backend.py
mopidy_plex/ext.conf
tests/__init__.py
tests/test_extension.py