Metadata-Version: 1.1
Name: Mopidy-Plex
Version: 0.1.0b
Summary: Mopidy extension for playing audio from a Plex server
Home-page: https://github.com/havardgulldahl/mopidy-plex
Author: Håvard Gulldahl
Author-email: havard@gulldahl.no
License: Apache License, Version 2.0
Platform: UNKNOWN
Classifier: Environment :: No Input/Output (Daemon)
Classifier: Intended Audience :: End Users/Desktop
Classifier: License :: OSI Approved :: Apache Software License
Classifier: Operating System :: OS Independent
Classifier: Programming Language :: Python :: 2
Classifier: Topic :: Multimedia :: Sound/Audio :: Players
